odoo9_addon_delivery_dropoff_site-9.0.1.0.1.99.dev3-nspkg.pth
odoo_addons/delivery_dropoff_site/README.rst
odoo_addons/delivery_dropoff_site/__init__.py
odoo_addons/delivery_dropoff_site/__openerp__.py
odoo_addons/delivery_dropoff_site/demo/delivery_carrier.xml
odoo_addons/delivery_dropoff_site/demo/dropoff_site.xml
odoo_addons/delivery_dropoff_site/demo/res_groups.xml
odoo_addons/delivery_dropoff_site/demo/resource_calendar.xml
odoo_addons/delivery_dropoff_site/i18n/delivery_dropoff_site.pot
odoo_addons/delivery_dropoff_site/i18n/fr.po
odoo_addons/delivery_dropoff_site/models/__init__.py
odoo_addons/delivery_dropoff_site/models/delivery_carrier.py
odoo_addons/delivery_dropoff_site/models/dropoff_site.py
odoo_addons/delivery_dropoff_site/models/procurement_group.py
odoo_addons/delivery_dropoff_site/models/res_partner.py
odoo_addons/delivery_dropoff_site/models/sale_order.py
odoo_addons/delivery_dropoff_site/models/stock_move.py
odoo_addons/delivery_dropoff_site/models/stock_picking.py
odoo_addons/delivery_dropoff_site/readme/CONFIGURE.rst
odoo_addons/delivery_dropoff_site/readme/CONTRIBUTORS.rst
odoo_addons/delivery_dropoff_site/readme/CREDITS.rst
odoo_addons/delivery_dropoff_site/readme/DESCRIPTION.rst
odoo_addons/delivery_dropoff_site/readme/USAGE.rst
odoo_addons/delivery_dropoff_site/security/ir.model.access.csv
odoo_addons/delivery_dropoff_site/static/description/dropoff_site_form.png
odoo_addons/delivery_dropoff_site/static/description/dropoff_site_form_calendar.png
odoo_addons/delivery_dropoff_site/static/description/dropoff_site_tree.png
odoo_addons/delivery_dropoff_site/static/description/icon.png
odoo_addons/delivery_dropoff_site/static/description/index.html
odoo_addons/delivery_dropoff_site/static/description/sale_order_form.png
odoo_addons/delivery_dropoff_site/views/view_delivery_carrier.xml
odoo_addons/delivery_dropoff_site/views/view_dropoff_site.xml
odoo_addons/delivery_dropoff_site/views/view_sale_order.xml
odoo9_addon_delivery_dropoff_site-9.0.1.0.1.99.dev3.dist-info/METADATA
odoo9_addon_delivery_dropoff_site-9.0.1.0.1.99.dev3.dist-info/WHEEL
odoo9_addon_delivery_dropoff_site-9.0.1.0.1.99.dev3.dist-info/namespace_packages.txt
odoo9_addon_delivery_dropoff_site-9.0.1.0.1.99.dev3.dist-info/top_level.txt
odoo9_addon_delivery_dropoff_site-9.0.1.0.1.99.dev3.dist-info/RECORD
